connectedcars/__init__.py
connectedcars/client.py
connectedcars/constants.py
connectedcars/exceptions.py
connectedcars/models.py
connectedcars-0.1.5.dist-info/LICENSE
connectedcars-0.1.5.dist-info/METADATA
connectedcars-0.1.5.dist-info/WHEEL
connectedcars-0.1.5.dist-info/top_level.txt
connectedcars-0.1.5.dist-info/RECORD
