Metadata-Version: 2.1
Name: connectedcars
Version: 0.1.5
Summary: Wrapper for access the Connected Cars API - an AVL/data collection service installed in most new danish vehicles from Audi, Volkswagen, Skoda and SEAT.
Home-page: https://github.com/niklascp/connectedcars-python
Author: Niklas Christoffer Petersen
Author-email: nikalscp@gmail.com
License: MIT
Download-URL: https://github.com/niklascp/connectedcars-python/archive/v0.1.4.tar.gz
Keywords: AVL,Audi,Volkswagen,Skoda,SEAT
Platform: UNKNOWN
Classifier: Intended Audience :: Developers
Classifier: License :: OSI Approved :: MIT License
Classifier: Programming Language :: Python :: 3.8
Classifier: Programming Language :: Python :: 3.9
Requires-Dist: aiohttp
Requires-Dist: attrs
Requires-Dist: python-dateutil
